pyneb/__init__.py
pyneb/__version__.py
pyneb/analysis.py
pyneb/fileio.py
pyneb/solvers.py
pyneb/utilities.py
python_neb-0.2.2.dist-info/LICENSE
python_neb-0.2.2.dist-info/METADATA
python_neb-0.2.2.dist-info/WHEEL
python_neb-0.2.2.dist-info/top_level.txt
python_neb-0.2.2.dist-info/RECORD
