Metadata-Version: 2.1
Name: python-neb
Version: 0.2.2
Summary: The Python Nudged Elastic Band Package
Author: Kyle Godbey, Daniel Lay, Eric Flynn
License: GNU GENERAL PUBLIC LICENSE
Classifier: Programming Language :: Python :: 3
Classifier: License :: OSI Approved :: GNU General Public License v3 (GPLv3)
Classifier: Operating System :: OS Independent
Requires-Python: >=3.9
License-File: LICENSE
Requires-Dist: certifi
Requires-Dist: cycler
Requires-Dist: h5py
Requires-Dist: kiwisolver
Requires-Dist: matplotlib
Requires-Dist: numpy
Requires-Dist: pathos
Requires-Dist: pyparsing
Requires-Dist: python-dateutil
Requires-Dist: scipy
Requires-Dist: six
Requires-Dist: numdifftools
